jipamlib_influxdb_v1/__init__.py
jipamlib_influxdb_v1/jutils.py
jipamlib_influxdb_v1-0.0.14.dist-info/METADATA
jipamlib_influxdb_v1-0.0.14.dist-info/WHEEL
jipamlib_influxdb_v1-0.0.14.dist-info/licenses/LICENSE
jipamlib_influxdb_v1-0.0.14.dist-info/RECORD
